testrail_mcp/__init__.py
testrail_mcp/__main__.py
testrail_mcp/config.py
testrail_mcp/mcp_server.py
testrail_mcp/testrail_client.py
testrail_mcp-0.1.5.dist-info/METADATA
testrail_mcp-0.1.5.dist-info/WHEEL
testrail_mcp-0.1.5.dist-info/entry_points.txt
testrail_mcp-0.1.5.dist-info/licenses/LICENSE
testrail_mcp-0.1.5.dist-info/RECORD
