Metadata-Version: 2.4
Name: testrail-mcp
Version: 0.1.5
Summary: TestRail MCP Server
Author-email: Stefan Rinke <sker65@gmail.com>
Maintainer-email: Stefan Rinke <sker65@gmail.com>
License: MIT
License-File: LICENSE
Requires-Python: >=3.10
Requires-Dist: fastmcp
Requires-Dist: python-dotenv>=1.0.0
Requires-Dist: python-mcp>=1.0.0
Requires-Dist: requests>=2.31.0
